getdates/__init__.py
getdates/cli.py
getdates-0.2.0.dist-info/METADATA
getdates-0.2.0.dist-info/WHEEL
getdates-0.2.0.dist-info/entry_points.txt
getdates-0.2.0.dist-info/top_level.txt
getdates-0.2.0.dist-info/RECORD
