Metadata-Version: 2.1
Name: getdates
Version: 0.2.0
Summary: A simple CLI tool to get current or previous datetime
Home-page: https://github.com/yourusername/getdates
Author: Your Name
Author-email: your.email@example.com
License: UNKNOWN
Platform: UNKNOWN
Classifier: Programming Language :: Python :: 3
Classifier: Operating System :: OS Independent
Requires-Python: >=3.7
